rectified_flow_pytorch/__init__.py
rectified_flow_pytorch/mean_flow.py
rectified_flow_pytorch/nano_flow.py
rectified_flow_pytorch/nano_flow_multi_obj.py
rectified_flow_pytorch/rectified_flow.py
rectified_flow_pytorch/reflow.py
rectified_flow_pytorch/soflow.py
rectified_flow_pytorch/split_mean_flow.py
rectified_flow_pytorch-0.5.3.dist-info/METADATA
rectified_flow_pytorch-0.5.3.dist-info/WHEEL
rectified_flow_pytorch-0.5.3.dist-info/licenses/LICENSE
rectified_flow_pytorch-0.5.3.dist-info/RECORD
