Metadata-Version: 2.4
Name: rectified-flow-pytorch
Version: 0.5.3
Summary: Rectified Flow in Pytorch
Project-URL: Homepage, https://pypi.org/project/rectified-flow-pytorch/
Project-URL: Repository, https://github.com/lucidrains/rectified-flow-pytorch
Author-email: Phil Wang <lucidrains@gmail.com>
License: MIT License
License-File: LICENSE
Keywords: artificial intelligence,deep learning,rectified flow
Classifier: Development Status :: 4 - Beta
Classifier: Intended Audience :: Developers
Classifier: License :: OSI Approved :: MIT License
Classifier: Programming Language :: Python :: 3.8
Classifier: Topic :: Scientific/Engineering :: Artificial Intelligence
Requires-Python: >=3.8
Requires-Dist: accelerate
Requires-Dist: einops>=0.8.0
Requires-Dist: einx>=0.3.0
Requires-Dist: ema-pytorch>=0.5.2
Requires-Dist: hyper-connections>=0.1.8
Requires-Dist: pillow>=9.4.0
Requires-Dist: scipy
Requires-Dist: torch>=2.0
Requires-Dist: torchdiffeq
Requires-Dist: torchvision
Provides-Extra: examples
Requires-Dist: datasets; extra == 'examples'
Provides-Extra: examples-fpo
Requires-Dist: adam-atan2-pytorch; extra == 'examples-fpo'
Requires-Dist: assoc-scan>=0.0.2; extra == 'examples-fpo'
Requires-Dist: box2d-py; extra == 'examples-fpo'
Requires-Dist: einops>=0.8.0; extra == 'examples-fpo'
Requires-Dist: einx>=0.3.0; extra == 'examples-fpo'
Requires-Dist: ema-pytorch>=0.7.3; extra == 'examples-fpo'
Requires-Dist: fire; extra == 'examples-fpo'
Requires-Dist: gymnasium[box2d]>=1.0.0; extra == 'examples-fpo'
Requires-Dist: hl-gauss-pytorch>=0.1.15; extra == 'examples-fpo'
Requires-Dist: hyper-connections>=0.2.0; extra == 'examples-fpo'
Requires-Dist: lion-pytorch; extra == 'examples-fpo'
Requires-Dist: moviepy>=1.0.3; extra == 'examples-fpo'
Requires-Dist: numpy>=2.2.5; extra == 'examples-fpo'
Requires-Dist: torch>=2.4; extra == 'examples-fpo'
Requires-Dist: tqdm; extra == 'examples-fpo'
Requires-Dist: x-transformers>=2.3.21; extra == 'examples-fpo'
Provides-Extra: examples-ql
Requires-Dist: assoc-scan; extra == 'examples-ql'
Requires-Dist: box2d-py; extra == 'examples-ql'
Requires-Dist: fire; extra == 'examples-ql'
Requires-Dist: gymnasium[box2d]>=1.0.0; extra == 'examples-ql'
Requires-Dist: moviepy>=1.0.3; extra == 'examples-ql'
Requires-Dist: numpy>=2.2.5; extra == 'examples-ql'
Requires-Dist: tqdm; extra == 'examples-ql'
Requires-Dist: x-mlps-pytorch>=0.0.20; extra == 'examples-ql'
Provides-Extra: test
Requires-Dist: pytest; extra == 'test'
